{"properties": [
  {
    "name": "stripe.api-url",
    "type": "java.lang.String",
    "description": "A description for 'stripe.api-url'"
  },
  {
    "name": "stripe.timeout",
    "type": "java.lang.String",
    "description": "A description for 'stripe.timeout'"
  },
  {
    "name": "stripe.enabled",
    "type": "java.lang.String",
    "description": "A description for 'stripe.enabled'"
  },
  {
    "name": "payment-gateway",
    "type": "java.lang.String",
    "description": "A description for 'payment-gateway'"
  },
  {
    "name": "mail.host",
    "type": "java.lang.String",
    "description": "A description for 'mail.host'"
  },
  {
    "name": "mail.port",
    "type": "java.lang.String",
    "description": "A description for 'mail.port'"
  },
  {
    "name": "spring.datasourсe.url",
    "type": "java.lang.String",
    "description": "A description for 'spring.datasourсe.url'"
  },
  {
    "name": "spring.datasourсe.username",
    "type": "java.lang.String",
    "description": "A description for 'spring.datasourсe.username'"
  },
  {
    "name": "spring.datasourсe.password",
    "type": "java.lang.String",
    "description": "A description for 'spring.datasourсe.password'"
  },
  {
    "name": "spring.datasourсe.driver-class-name",
    "type": "java.lang.String",
    "description": "A description for 'spring.datasourсe.driver-class-name'"
  },
  {
    "name": "stripe.supported-currencies",
    "type": "java.lang.String",
    "description": "A description for 'stripe.supported-currencies'"
  }
]}